buildfile/build.py
src/__init__.py
src/instruction/__init__.py
src/instruction/instruct.py
instructos-0.2.1.dist-info/METADATA
instructos-0.2.1.dist-info/WHEEL
instructos-0.2.1.dist-info/licenses/LICENSE
instructos-0.2.1.dist-info/RECORD
