Metadata-Version: 2.1
Name: instructOS
Version: 0.2.1
Summary: The database of instruction set for Operating System
Project-URL: Homepage, https://github.com/tooig/instruction
Project-URL: Bug Tracker, https://github.com/tooig/instruction/issues
Author-email: "Tooig, Inc" <tooighq@gmail.com>, Oyebamijo <gloryoyebamijo@gmail.com>
License-File: LICENSE
Classifier: License :: OSI Approved :: MIT License
Classifier: Operating System :: OS Independent
Classifier: Programming Language :: Python :: 3
Requires-Python: >=3.8
